{"5236078/5218411/5241045?Route=stories": {"title": "Denis Brown", "bib": ["The Schools\u2019 Collection", "Volume 0088E", "Page\u00a014_005"], "url": "https://www.duchas.ie/en/cbes/5236078/5218411/5241045?Route=stories", "school_info": "Achadh Fobhair (roll number 13853)", "metadata": [{"Location:": "Aghagower, Co. Mayo "}, {"Topics": "agents (~1)\n\t\t\t\t historical persons (~5,068)\n\t\t\t\t Denis Browne (Denis of the Rope) (~25)\n\t\t\t\t      ", "Language": "English ", "Location": "Mountbrown, Co. Mayo "}, {"Collector": "Kathleen Mc Donagh  ", "Gender": "Male", "Address": "Mountbrown, Co. Mayo "}, {"Content and data:": "\u00a9 2023 National Folklore Collection, UCD ", "Technical solution:": "\u00a9 2023 Gaois, Fiontar & Scoil na Gaeilge, DCU\n\t\t\t\t", "Contact:": "eolas@duchas.ie", "Social media:": " Facebook  Twitter"}]}, "4427840/4349265/4440069?Route=stories": {"title": "Stories Relating to Denis\u00a0Browne", "bib": ["The Schools\u2019 Collection", "Volume 0096", "Page\u00a0482"], "url": "https://www.duchas.ie/en/cbes/4427840/4349265/4440069?Route=stories", "school_info": "Baile an Daingin (C.) (roll number 4828)", "metadata": [{"Location:": "Ballindine, Co. Mayo "}, {"Topics": "agents (~1)\n\t\t\t\t historical persons (~5,068)\n\t\t\t\t Denis Browne (Denis of the Rope) (~25)\n\t\t\t\t      ", "Language": "English "}, {"Collector": "Maura Waldron  ", "Gender": "Female"}, {"Informant": "Michael Daly  ", "Gender": "Male", "Age": "c. 80 ", "Address": "Boleyboy, Co. Mayo "}, {"Content and data:": "\u00a9 2023 National Folklore Collection, UCD ", "Technical solution:": "\u00a9 2023 Gaois, Fiontar & Scoil na Gaeilge, DCU\n\t\t\t\t", "Contact:": "eolas@duchas.ie", "Social media:": " Facebook  Twitter"}]}, "4427840/4349266/4440070?Route=stories": {"title": "Stories Relating to Denis\u00a0Browne", "bib": ["The Schools\u2019 Collection", "Volume 0096", "Page\u00a0483"], "url": "https://www.duchas.ie/en/cbes/4427840/4349266/4440070?Route=stories", "school_info": "Baile an Daingin (C.) (roll number 4828)", "metadata": [{"Location:": "Ballindine, Co. Mayo "}, {"Topics": "agents (~1)\n\t\t\t\t historical persons (~5,068)\n\t\t\t\t Denis Browne (Denis of the Rope) (~25)\n\t\t\t\t      ", "Language": "English "}, {"Collector": "Kathleen Hynes  ", "Gender": "Female"}, {"Informant": "Petter Fahy  ", "Gender": "Male", "Age": "c. 73 ", "Address": "Ballindine, Co. Mayo "}, {"Content and data:": "\u00a9 2023 National Folklore Collection, UCD ", "Technical solution:": "\u00a9 2023 Gaois, Fiontar & Scoil na Gaeilge, DCU\n\t\t\t\t", "Contact:": "eolas@duchas.ie", "Social media:": " Facebook  Twitter"}]}, "4427840/4349268/4440071?Route=stories": {"title": "Stories Relating to Denis\u00a0Browne", "bib": ["The Schools\u2019 Collection", "Volume 0096", "Page\u00a0485"], "url": "https://www.duchas.ie/en/cbes/4427840/4349268/4440071?Route=stories", "school_info": "Baile an Daingin (C.) (roll number 4828)", "metadata": [{"Location:": "Ballindine, Co. Mayo "}, {"Topics": "agents (~1)\n\t\t\t\t historical persons (~5,068)\n\t\t\t\t Denis Browne (Denis of the Rope) (~25)\n\t\t\t\t     time historical periods by name (~25)\n\t\t\t\t penal times (~4,335)\n\t\t\t\t      ", "Language": "English "}, {"Collector": "Margaret Slattery  ", "Gender": "Female"}, {"Informant": "Thomas Mc Hugh  ", "Gender": "Male", "Age": " 66 "}, {"Content and data:": "\u00a9 2023 National Folklore Collection, UCD ", "Technical solution:": "\u00a9 2023 Gaois, Fiontar & Scoil na Gaeilge, DCU\n\t\t\t\t", "Contact:": "eolas@duchas.ie", "Social media:": " Facebook  Twitter"}]}, "4427840/4349271/4440072?Route=stories": {"title": "Stories Relating to Denis\u00a0Browne", "bib": ["The Schools\u2019 Collection", "Volume 0096", "Page\u00a0488"], "url": "https://www.duchas.ie/en/cbes/4427840/4349271/4440072?Route=stories", "school_info": "Baile an Daingin (C.) (roll number 4828)", "metadata": [{"Location:": "Ballindine, Co. Mayo "}, {"Topics": "agents (~1)\n\t\t\t\t historical persons (~5,068)\n\t\t\t\t Denis Browne (Denis of the Rope) (~25)\n\t\t\t\t     time historical periods by name (~25)\n\t\t\t\t penal times (~4,335)\n\t\t\t\t      ", "Language": "English "}, {"Collector": "May Joyce  ", "Gender": "Female", "Address": "Ballyglass, Co. Mayo "}, {"Informant": "Patrick Joyce  ", "Gender": "Male", "Age": " 64 ", "Address": "Ballyglass, Co. Mayo "}, {"Content and data:": "\u00a9 2023 National Folklore Collection, UCD ", "Technical solution:": "\u00a9 2023 Gaois, Fiontar & Scoil na Gaeilge, DCU\n\t\t\t\t", "Contact:": "eolas@duchas.ie", "Social media:": " Facebook  Twitter"}]}, "4427840/4349272/4440073?Route=stories": {"title": "Stories Relating to Denis\u00a0Browne", "bib": ["The Schools\u2019 Collection", "Volume 0096", "Page\u00a0489"], "url": "https://www.duchas.ie/en/cbes/4427840/4349272/4440073?Route=stories", "school_info": "Baile an Daingin (C.) (roll number 4828)", "metadata": [{"Location:": "Ballindine, Co. Mayo "}, {"Topics": "agents (~1)\n\t\t\t\t historical persons (~5,068)\n\t\t\t\t Denis Browne (Denis of the Rope) (~25)\n\t\t\t\t     time historical periods by name (~25)\n\t\t\t\t penal times (~4,335)\n\t\t\t\t      ", "Language": "English "}, {"Collector": "Eithne Griffith  ", "Gender": "Female"}, {"Informant": "M.J. Kilkelly  ", "Age": " 56 ", "Address": "Ballindine, Co. Mayo "}, {"Content and data:": "\u00a9 2023 National Folklore Collection, UCD ", "Technical solution:": "\u00a9 2023 Gaois, Fiontar & Scoil na Gaeilge, DCU\n\t\t\t\t", "Contact:": "eolas@duchas.ie", "Social media:": " Facebook  Twitter"}]}, "4427840/4349272/4440074?Route=stories": {"title": "Stories Relating to Denis\u00a0Browne", "bib": ["Baili\u00fach\u00e1n na Scol", "Imleabhar 0096", "Leathanach\u00a0489"], "url": "https://www.duchas.ie/en/cbes/4427840/4349272/4440074?Route=stories", "school_info": "Baile an Daingin (C.) (uimhir rolla 4828)", "metadata": [{"Su\u00edomh:": "Ballindine, Co. Mayo "}, {"Topaic\u00ed": "agents (~1)\n\t\t\t\t historical persons (~5,068)\n\t\t\t\t Denis Browne (Denis of the Rope) (~25)\n\t\t\t\t     time historical periods by name (~25)\n\t\t\t\t penal times (~4,335)\n\t\t\t\t      ", "Teanga": "B\u00e9arla "}, {"Bailitheoir": "Benny O' Connor  ", "Inscne": "Fireann"}, {"Faisn\u00e9iseoir": "Michael Bane  ", "Inscne": "Fireann", "Aois": " 71 ", "Seoladh": "Kilvine, Co. Mayo "}, {"\u00c1bhar agus sonra\u00ed:": "\u00a9 2023 Cnuasach Bh\u00e9aloideas \u00c9ireann, UCD ", "R\u00e9iteach teicni\u00fail:": "\u00a9 2023 Gaois, Fiontar & Scoil na Gaeilge, DCU\n\t\t\t\t", "Teagmh\u00e1il:": "eolas@duchas.ie", "Ar na me\u00e1in sh\u00f3isialta:": " Facebook  Twitter"}]}, "4427840/4349275/4440075?Route=stories": {"title": "Stories Relating to Denis\u00a0Browne", "bib": ["The Schools\u2019 Collection", "Volume 0096", "Page\u00a0491"], "url": "https://www.duchas.ie/en/cbes/4427840/4349275/4440075?Route=stories", "school_info": "Baile an Daingin (C.) (roll number 4828)", "metadata": [{"Location:": "Ballindine, Co. Mayo "}, {"Topics": "agents (~1)\n\t\t\t\t historical persons (~5,068)\n\t\t\t\t Denis Browne (Denis of the Rope) (~25)\n\t\t\t\t     time historical periods by name (~25)\n\t\t\t\t penal times (~4,335)\n\t\t\t\t      ", "Language": "English "}, {"Collector": "Atractia Rhatigan  ", "Gender": "Female"}, {"Informant": "Thomas Rhatigan  ", "Gender": "Male", "Age": " 60 ", "Address": "Carrownurlaur, Co. Galway "}, {"Content and data:": "\u00a9 2023 National Folklore Collection, UCD ", "Technical solution:": "\u00a9 2023 Gaois, Fiontar & Scoil na Gaeilge, DCU\n\t\t\t\t", "Contact:": "eolas@duchas.ie", "Social media:": " Facebook  Twitter"}]}, "4427840/4349277/4440076?Route=stories": {"title": "Stories Relating to Denis\u00a0Browne", "bib": ["The Schools\u2019 Collection", "Volume 0096", "Page\u00a0493"], "url": "https://www.duchas.ie/en/cbes/4427840/4349277/4440076?Route=stories", "school_info": "Baile an Daingin (C.) (roll number 4828)", "metadata": [{"Location:": "Ballindine, Co. Mayo "}, {"Topics": "agents (~1)\n\t\t\t\t historical persons (~5,068)\n\t\t\t\t Denis Browne (Denis of the Rope) (~25)\n\t\t\t\t      ", "Language": "English "}, {"Collector": "Eithne Griffith  ", "Gender": "Female"}, {"Informant": "Thomas Keary  ", "Gender": "Male", "Age": "c. 60 ", "Address": "Ballindine, Co. Mayo "}, {"Content and data:": "\u00a9 2023 National Folklore Collection, UCD ", "Technical solution:": "\u00a9 2023 Gaois, Fiontar & Scoil na Gaeilge, DCU\n\t\t\t\t", "Contact:": "eolas@duchas.ie", "Social media:": " Facebook  Twitter"}]}, "4427840/4349277/4440080?Route=stories": {"title": "Stories Relating to Denis\u00a0Browne", "bib": ["The Schools\u2019 Collection", "Volume 0096", "Page\u00a0493"], "url": "https://www.duchas.ie/en/cbes/4427840/4349277/4440080?Route=stories", "school_info": "Baile an Daingin (C.) (roll number 4828)", "metadata": [{"Location:": "Ballindine, Co. Mayo "}, {"Topics": "agents (~1)\n\t\t\t\t historical persons (~5,068)\n\t\t\t\t Denis Browne (Denis of the Rope) (~25)\n\t\t\t\t      ", "Language": "English "}, {"Collector": "Sara Devane  ", "Gender": "Female"}, {"Informant": "John Duddy  ", "Gender": "Male", "Age": " 70 ", "Address": "Killeen, Co. Mayo "}, {"Content and data:": "\u00a9 2023 National Folklore Collection, UCD ", "Technical solution:": "\u00a9 2023 Gaois, Fiontar & Scoil na Gaeilge, DCU\n\t\t\t\t", "Contact:": "eolas@duchas.ie", "Social media:": " Facebook  Twitter"}]}, "4427842/4349660/4440683?Route=stories": {"title": "Denis Browne", "bib": ["The Schools\u2019 Collection", "Volume 0097", "Page\u00a023"], "url": "https://www.duchas.ie/en/cbes/4427842/4349660/4440683?Route=stories", "school_info": "Baile an Daingin (B) (roll number 1676)", "metadata": [{"Location:": "Ballindine, Co. Mayo "}, {"Topics": "agents (~1)\n\t\t\t\t historical persons (~5,068)\n\t\t\t\t Denis Browne (Denis of the Rope) (~25)\n\t\t\t\t      ", "Language": "English "}, {"Collector": "James Rhatigan  ", "Gender": "Male", "Address": "Carrownurlaur, Co. Galway "}, {"Informant": "John Macken  ", "Gender": "Male", "Age": " 70 ", "Address": "Carrownurlaur, Co. Galway "}, {"Content and data:": "\u00a9 2023 National Folklore Collection, UCD ", "Technical solution:": "\u00a9 2023 Gaois, Fiontar & Scoil na Gaeilge, DCU\n\t\t\t\t", "Contact:": "eolas@duchas.ie", "Social media:": " Facebook  Twitter"}]}, "4427842/4349704/4440686?Route=stories": {"title": "Denis Browne", "bib": ["The Schools\u2019 Collection", "Volume 0097", "Page\u00a027"], "url": "https://www.duchas.ie/en/cbes/4427842/4349704/4440686?Route=stories", "school_info": "Baile an Daingin (B) (roll number 1676)", "metadata": [{"Location:": "Ballindine, Co. Mayo "}, {"Topics": "agents (~1)\n\t\t\t\t historical persons (~5,068)\n\t\t\t\t Denis Browne (Denis of the Rope) (~25)\n\t\t\t\t      ", "Language": "English "}, {"Collector": "James Cleary  ", "Gender": "Male", "Address": "Cloonmore, Co. Mayo "}, {"Informant": "Margaret Kilkenny  ", "Gender": "Female", "Age": " 73 ", "Address": "Cloonmore, Co. Mayo "}, {"Content and data:": "\u00a9 2023 National Folklore Collection, UCD ", "Technical solution:": "\u00a9 2023 Gaois, Fiontar & Scoil na Gaeilge, DCU\n\t\t\t\t", "Contact:": "eolas@duchas.ie", "Social media:": " Facebook  Twitter"}]}, "4427842/4349715/4440948?Route=stories": {"title": "Denis Browne", "bib": ["The Schools\u2019 Collection", "Volume 0097", "Page\u00a028"], "url": "https://www.duchas.ie/en/cbes/4427842/4349715/4440948?Route=stories", "school_info": "Baile an Daingin (B) (roll number 1676)", "metadata": [{"Location:": "Ballindine, Co. Mayo "}, {"Topics": "agents (~1)\n\t\t\t\t historical persons (~5,068)\n\t\t\t\t Denis Browne (Denis of the Rope) (~25)\n\t\t\t\t      ", "Language": "English "}, {"Collector": "James Kivneen  ", "Gender": "Male", "Address": "Lugalisheen South, Co. Mayo "}, {"Informant": "Patrick Kivneen  ", "Gender": "Male", "Age": " 46 ", "Address": "Lugalisheen South, Co. Mayo "}, {"Content and data:": "\u00a9 2023 National Folklore Collection, UCD ", "Technical solution:": "\u00a9 2023 Gaois, Fiontar & Scoil na Gaeilge, DCU\n\t\t\t\t", "Contact:": "eolas@duchas.ie", "Social media:": " Facebook  Twitter"}]}, "4427853/4350774/4453291?Route=stories": {"title": "Denis Brown", "bib": ["The Schools\u2019 Collection", "Volume 0099", "Page\u00a0077"], "url": "https://www.duchas.ie/en/cbes/4427853/4350774/4453291?Route=stories", "school_info": "Koilmore (roll number 14115)", "metadata": [{"Location:": "Cuilmore, Co. Mayo "}, {"Topics": "agents (~1)\n\t\t\t\t historical persons (~5,068)\n\t\t\t\t Denis Browne (Denis of the Rope) (~25)\n\t\t\t\t      ", "Language": "English "}, {"Informant": "Michael Fleming  ", "Gender": "Male", "Age": " 45 ", "Address": "Garryredmond, Co. Mayo "}, {"Content and data:": "\u00a9 2023 National Folklore Collection, UCD ", "Technical solution:": "\u00a9 2023 Gaois, Fiontar & Scoil na Gaeilge, DCU\n\t\t\t\t", "Contact:": "eolas@duchas.ie", "Social media:": " Facebook  Twitter"}]}, "4427853/4350787/4453363?Route=stories": {"title": "Denis Browne", "bib": ["The Schools\u2019 Collection", "Volume 0099", "Page\u00a0090"], "url": "https://www.duchas.ie/en/cbes/4427853/4350787/4453363?Route=stories", "school_info": "Koilmore (roll number 14115)", "metadata": [{"Location:": "Cuilmore, Co. Mayo "}, {"Topics": "agents (~1)\n\t\t\t\t historical persons (~5,068)\n\t\t\t\t Denis Browne (Denis of the Rope) (~25)\n\t\t\t\t      ", "Language": "English "}, {"Informant": "Patrick Clarke  ", "Gender": "Male", "Age": " 45 ", "Address": "Ballyglass, Co. Mayo "}, {"Content and data:": "\u00a9 2023 National Folklore Collection, UCD ", "Technical solution:": "\u00a9 2023 Gaois, Fiontar & Scoil na Gaeilge, DCU\n\t\t\t\t", "Contact:": "eolas@duchas.ie", "Social media:": " Facebook  Twitter"}]}, "4427853/4350788/4453366?Route=stories": {"title": "Denis Browne", "bib": ["The Schools\u2019 Collection", "Volume 0099", "Page\u00a0091"], "url": "https://www.duchas.ie/en/cbes/4427853/4350788/4453366?Route=stories", "school_info": "Koilmore (roll number 14115)", "metadata": [{"Location:": "Cuilmore, Co. Mayo "}, {"Topics": "agents (~1)\n\t\t\t\t historical persons (~5,068)\n\t\t\t\t Denis Browne (Denis of the Rope) (~25)\n\t\t\t\t      ", "Language": "English "}, {"Informant": "Mrs Gibbons  ", "Gender": "Female", "Age": " 75 ", "Address": "Ballinagran, Co. Mayo "}, {"Content and data:": "\u00a9 2023 National Folklore Collection, UCD ", "Technical solution:": "\u00a9 2023 Gaois, Fiontar & Scoil na Gaeilge, DCU\n\t\t\t\t", "Contact:": "eolas@duchas.ie", "Social media:": " Facebook  Twitter"}]}, "4427853/4350789/4453377?Route=stories": {"title": "Denis Browne", "bib": ["The Schools\u2019 Collection", "Volume 0099", "Page\u00a0092"], "url": "https://www.duchas.ie/en/cbes/4427853/4350789/4453377?Route=stories", "school_info": "Koilmore (roll number 14115)", "metadata": [{"Location:": "Cuilmore, Co. Mayo "}, {"Topics": "agents (~1)\n\t\t\t\t historical persons (~5,068)\n\t\t\t\t Denis Browne (Denis of the Rope) (~25)\n\t\t\t\t      ", "Language": "English "}, {"Informant": "Thomas Mongan  ", "Gender": "Male", "Age": " 65 ", "Address": "Ballygowan, Co. Mayo "}, {"Content and data:": "\u00a9 2023 National Folklore Collection, UCD ", "Technical solution:": "\u00a9 2023 Gaois, Fiontar & Scoil na Gaeilge, DCU\n\t\t\t\t", "Contact:": "eolas@duchas.ie", "Social media:": " Facebook  Twitter"}]}, "4427853/4350791/4453384?Route=stories": {"title": "Denis Brown and His\u00a0Hangmen", "bib": ["The Schools\u2019 Collection", "Volume 0099", "Page\u00a0094"], "url": "https://www.duchas.ie/en/cbes/4427853/4350791/4453384?Route=stories", "school_info": "Koilmore (roll number 14115)", "metadata": [{"Location:": "Cuilmore, Co. Mayo "}, {"Topics": "agents (~1)\n\t\t\t\t historical persons (~5,068)\n\t\t\t\t Denis Browne (Denis of the Rope) (~25)\n\t\t\t\t   supernatural and legendary beings (~14,864)\n\t\t\t\t    ", "Language": "English "}, {"Informant": "Michael Fleming  ", "Gender": "Male", "Age": " 45 ", "Address": "Garryredmond, Co. Mayo "}, {"Content and data:": "\u00a9 2023 National Folklore Collection, UCD ", "Technical solution:": "\u00a9 2023 Gaois, Fiontar & Scoil na Gaeilge, DCU\n\t\t\t\t", "Contact:": "eolas@duchas.ie", "Social media:": " Facebook  Twitter"}]}, "5215809/5213893/5221505?Route=stories": {"title": "Denis Brown", "bib": ["The Schools\u2019 Collection", "Volume 0137F", "Page\u00a002_019"], "url": "https://www.duchas.ie/en/cbes/5215809/5213893/5221505?Route=stories", "school_info": "Lankill (roll number 16904)", "metadata": [{"Location:": "Lankill, Co. Mayo "}, {"Topics": "agents (~1)\n\t\t\t\t historical persons (~5,068)\n\t\t\t\t Denis Browne (Denis of the Rope) (~25)\n\t\t\t\t      ", "Language": "English "}, {"Collector": "Martin King  ", "Gender": "Male", "Address": "Lanmore, Co. Mayo "}, {"Informant": "John Walsh  ", "Gender": "Male", "Address": "Lanmore, Co. Mayo "}, {"Content and data:": "\u00a9 2023 National Folklore Collection, UCD ", "Technical solution:": "\u00a9 2023 Gaois, Fiontar & Scoil na Gaeilge, DCU\n\t\t\t\t", "Contact:": "eolas@duchas.ie", "Social media:": " Facebook  Twitter"}]}, "5215809/5213936/5221623?Route=stories": {"title": "Denis Brown", "bib": ["The Schools\u2019 Collection", "Volume 0137F", "Page\u00a003_023"], "url": "https://www.duchas.ie/en/cbes/5215809/5213936/5221623?Route=stories", "school_info": "Lankill (roll number 16904)", "metadata": [{"Location:": "Lankill, Co. Mayo "}, {"Topics": "agents (~1)\n\t\t\t\t historical persons (~5,068)\n\t\t\t\t Denis Browne (Denis of the Rope) (~25)\n\t\t\t\t      ", "Language": "English "}, {"Collector": "Nora O Boyle  ", "Gender": "Female", "Address": "Ballyballinaun, Co. Mayo "}, {"Informant": "Timothy O Boyle  ", "Gender": "Male", "Address": "Ballyballinaun, Co. Mayo "}, {"Content and data:": "\u00a9 2023 National Folklore Collection, UCD ", "Technical solution:": "\u00a9 2023 Gaois, Fiontar & Scoil na Gaeilge, DCU\n\t\t\t\t", "Contact:": "eolas@duchas.ie", "Social media:": " Facebook  Twitter"}]}, "5215809/5231463/5265054?Route=stories": {"title": "Denis Brown", "bib": ["The Schools\u2019 Collection", "Volume 0137F", "Page\u00a012_079"], "url": "https://www.duchas.ie/en/cbes/5215809/5231463/5265054?Route=stories", "school_info": "Lankill (roll number 16904)", "metadata": [{"Location:": "Lankill, Co. Mayo "}, {"Topics": "agents (~1)\n\t\t\t\t historical persons (~5,068)\n\t\t\t\t Denis Browne (Denis of the Rope) (~25)\n\t\t\t\t      ", "Language": "English ", "Location": "Mountbrown, Co. Mayo "}, {"Collector": "Eileen King  ", "Gender": "Female", "Address": "Lanmore, Co. Mayo "}, {"Informant": "Tom King  ", "Gender": "Male", "Address": "Lanmore, Co. Mayo "}, {"Content and data:": "\u00a9 2023 National Folklore Collection, UCD ", "Technical solution:": "\u00a9 2023 Gaois, Fiontar & Scoil na Gaeilge, DCU\n\t\t\t\t", "Contact:": "eolas@duchas.ie", "Social media:": " Facebook  Twitter"}]}, "5215809/5231465/5265057?Route=stories": {"title": "Denis Brown and the\u00a0Tramp", "bib": ["The Schools\u2019 Collection", "Volume 0137F", "Page\u00a012_081"], "url": "https://www.duchas.ie/en/cbes/5215809/5231465/5265057?Route=stories", "school_info": "Lankill (roll number 16904)", "metadata": [{"Location:": "Lankill, Co. Mayo "}, {"Topics": "agents (~1)\n\t\t\t\t historical persons (~5,068)\n\t\t\t\t Denis Browne (Denis of the Rope) (~25)\n\t\t\t\t      ", "Language": "English "}, {"Collector": "Eileen King  ", "Gender": "Female", "Address": "Lanmore, Co. Mayo "}, {"Informant": "John Walsh  ", "Gender": "Male", "Address": "Lanmore, Co. Mayo "}, {"Content and data:": "\u00a9 2023 National Folklore Collection, UCD ", "Technical solution:": "\u00a9 2023 Gaois, Fiontar & Scoil na Gaeilge, DCU\n\t\t\t\t", "Contact:": "eolas@duchas.ie", "Social media:": " Facebook  Twitter"}]}, "5215809/5214071/5221682?Route=stories": {"title": "People Hanged by Denis\u00a0Brown", "bib": ["The Schools\u2019 Collection", "Volume 0137F", "Page\u00a005_053"], "url": "https://www.duchas.ie/en/cbes/5215809/5214071/5221682?Route=stories", "school_info": "Lankill (roll number 16904)", "metadata": [{"Location:": "Lankill, Co. Mayo "}, {"Topics": "agents (~1)\n\t\t\t\t historical persons (~5,068)\n\t\t\t\t Denis Browne (Denis of the Rope) (~25)\n\t\t\t\t      ", "Language": "English "}, {"Collector": "Mary Keane  ", "Gender": "Female", "Address": "Ballinlough, Co. Mayo "}, {"Informant": "Mr Hugh Keane  ", "Gender": "Male", "Address": "Ballinlough, Co. Mayo "}, {"Content and data:": "\u00a9 2023 National Folklore Collection, UCD ", "Technical solution:": "\u00a9 2023 Gaois, Fiontar & Scoil na Gaeilge, DCU\n\t\t\t\t", "Contact:": "eolas@duchas.ie", "Social media:": " Facebook  Twitter"}]}, "5215809/5231778/5265842?Route=stories": {"title": "Denis Brown's Castle", "bib": ["The Schools\u2019 Collection", "Volume 0137F", "Page\u00a019_061"], "url": "https://www.duchas.ie/en/cbes/5215809/5231778/5265842?Route=stories", "school_info": "Lankill (roll number 16904)", "metadata": [{"Location:": "Lankill, Co. Mayo "}, {"Topics": "agents (~1)\n\t\t\t\t historical persons (~5,068)\n\t\t\t\t Denis Browne (Denis of the Rope) (~25)\n\t\t\t\t      ", "Language": "English "}, {"Collector": "Kitty Duffy  ", "Gender": "Female", "Address": "Lanmore, Co. Mayo "}, {"Informant": "Tom Mc Guire  ", "Gender": "Male", "Address": "Lanmore, Co. Mayo "}, {"Content and data:": "\u00a9 2023 National Folklore Collection, UCD ", "Technical solution:": "\u00a9 2023 Gaois, Fiontar & Scoil na Gaeilge, DCU\n\t\t\t\t", "Contact:": "eolas@duchas.ie", "Social media:": " Facebook  Twitter"}]}, "4428071/4375019/4457331?Route=stories": {"title": "Soap the\u00a0Rope", "bib": ["The Schools\u2019 Collection", "Volume 0151", "Page\u00a0353"], "url": "https://www.duchas.ie/en/cbes/4428071/4375019/4457331?Route=stories", "school_info": "Droichead na Daoile (roll number 14736)", "metadata": [{"Location:": "Lackalustraun, Co. Mayo "}, {"Topics": "agents (~1)\n\t\t\t\t historical persons (~5,068)\n\t\t\t\t Denis Browne (Denis of the Rope) (~25)\n\t\t\t\t      ", "Language": "English "}, {"Collector": "Maura Gallagher  ", "Gender": "Female", "Address": "Mungaun, Co. Mayo "}, {"Informant": "James Gallagher  ", "Gender": "Male", "Age": " 48 ", "Address": "Mungaun, Co. Mayo "}, {"Content and data:": "\u00a9 2023 National Folklore Collection, UCD ", "Technical solution:": "\u00a9 2023 Gaois, Fiontar & Scoil na Gaeilge, DCU\n\t\t\t\t", "Contact:": "eolas@duchas.ie", "Social media:": " Facebook  Twitter"}]}}